odoo/addons/ssi_mia_daily_summary_py3o_report/README.rst
odoo/addons/ssi_mia_daily_summary_py3o_report/__init__.py
odoo/addons/ssi_mia_daily_summary_py3o_report/__manifest__.py
odoo/addons/ssi_mia_daily_summary_py3o_report/reports/__init__.py
odoo/addons/ssi_mia_daily_summary_py3o_report/reports/daily_summary_template.ods
odoo/addons/ssi_mia_daily_summary_py3o_report/reports/hr_daily_summary_report.py
odoo/addons/ssi_mia_daily_summary_py3o_report/reports/hr_daily_summary_reports.xml
odoo/addons/ssi_mia_daily_summary_py3o_report/security/ir.model.access.csv
odoo/addons/ssi_mia_daily_summary_py3o_report/static/description/icon.png
odoo/addons/ssi_mia_daily_summary_py3o_report/wizards/__init__.py
odoo/addons/ssi_mia_daily_summary_py3o_report/wizards/hr_print_daily_summary.py
odoo/addons/ssi_mia_daily_summary_py3o_report/wizards/hr_print_daily_summary_views.xml
odoo14_addon_ssi_mia_daily_summary_py3o_report-14.0.1.1.0.dist-info/METADATA
odoo14_addon_ssi_mia_daily_summary_py3o_report-14.0.1.1.0.dist-info/WHEEL
odoo14_addon_ssi_mia_daily_summary_py3o_report-14.0.1.1.0.dist-info/top_level.txt
odoo14_addon_ssi_mia_daily_summary_py3o_report-14.0.1.1.0.dist-info/RECORD
